amethyst_facet/__init__.py
amethyst_facet/__main__.py
amethyst_facet/cli/__init__.py
amethyst_facet/cli/commands/__init__.py
amethyst_facet/cli/commands/agg.py
amethyst_facet/cli/commands/calls2h5.py
amethyst_facet/cli/commands/convert.py
amethyst_facet/cli/commands/delete.py
amethyst_facet/cli/commands/facet.py
amethyst_facet/cli/commands/version.py
amethyst_facet/cli/decorators/__init__.py
amethyst_facet/cli/decorators/decorators.py
amethyst_facet/cli/parse/__init__.py
amethyst_facet/cli/parse/cli_options_parser.py
amethyst_facet/cli/parse/uniform_windows_parser.py
amethyst_facet/cli/parse/variable_windows_parser.py
amethyst_facet/errors/__init__.py
amethyst_facet/errors/error_handling.py
amethyst_facet/h5/__init__.py
amethyst_facet/h5/dataset.py
amethyst_facet/h5/handles.py
amethyst_facet/h5/reader.py
amethyst_facet/h5/readerv1.py
amethyst_facet/h5/readerv2.py
amethyst_facet/windows/__init__.py
amethyst_facet/windows/uniform_windows_aggregator.py
amethyst_facet/windows/variable_windows_aggregator.py
amethyst_facet/windows/windows_aggregator.py
amethyst_facet-1.2.4.dist-info/METADATA
amethyst_facet-1.2.4.dist-info/WHEEL
amethyst_facet-1.2.4.dist-info/entry_points.txt
amethyst_facet-1.2.4.dist-info/RECORD
