Metadata-Version: 2.4
Name: amethyst-facet
Version: 1.2.4
Summary: Compute window aggregations and alter contents of Amethyst HDF5 files
Author: Ben Skubi
Author-email: skubi@ohsu.edu
Requires-Python: >=3.12,<4.0
Classifier: Programming Language :: Python :: 3
Classifier: Programming Language :: Python :: 3.12
Classifier: Programming Language :: Python :: 3.13
Classifier: Programming Language :: Python :: 3.14
Requires-Dist: click
Requires-Dist: duckdb
Requires-Dist: h5py
Requires-Dist: hypothesis
Requires-Dist: loguru (>=0.7.3,<0.8.0)
Requires-Dist: numpy (<=1.26.4)
Requires-Dist: pandas
Requires-Dist: parse
Requires-Dist: polars (==1.31.0)
Requires-Dist: pyarrow
Requires-Dist: pydantic (>=2.12.4,<3.0.0)
Requires-Dist: pytest
Requires-Dist: rich (>=14.2.0,<15.0.0)
